SmartAnno/Eval.py
SmartAnno/__init__.py
SmartAnno/conf/DefaultRules.py
SmartAnno/conf/__init__.py
SmartAnno/conf/general_modifiers.yml
SmartAnno/conf/rush_rules.tsv
SmartAnno/conf/smartanno_conf.json.bk
SmartAnno/db/ORMs.py
SmartAnno/db/__init__.py
SmartAnno/gui/BranchingWidgets.py
SmartAnno/gui/DirChooser.py
SmartAnno/gui/ExternalWidgets.py
SmartAnno/gui/FileChooser.py
SmartAnno/gui/FileIO.py
SmartAnno/gui/Main.py
SmartAnno/gui/MyWidgets.py
SmartAnno/gui/PreviousNextWidgets.py
SmartAnno/gui/Workflow.py
SmartAnno/gui/__init__.py
SmartAnno/models/BaseClassifier.py
SmartAnno/models/GloveModel.py
SmartAnno/models/__init__.py
SmartAnno/models/cnn/CnnModel.py
SmartAnno/models/cnn/PreProcessing.py
SmartAnno/models/cnn/__init__.py
SmartAnno/models/logistic/LogisticBOWClassifier.py
SmartAnno/models/logistic/__init__.py
SmartAnno/models/rulebased/RBDocumentClassifier.py
SmartAnno/models/rulebased/__init__.py
SmartAnno/models/rulebased/itemData.py
SmartAnno/models/rulebased/nlp_pneumonia_utils.py
SmartAnno/models/rulebased/visual.py
SmartAnno/models/sampling/BaseSampler.py
SmartAnno/models/sampling/KeywordStratefiedSampler.py
SmartAnno/models/sampling/__init__.py
SmartAnno/models/svm/SVMBOWClassifier.py
SmartAnno/models/svm/SVMClassifier.py
SmartAnno/models/svm/__init__.py
SmartAnno/umls/Authentication.py
SmartAnno/umls/UMLSFinder.py
SmartAnno/umls/__init__.py
SmartAnno/umls/walk_hierarchy.py
SmartAnno/utils/AnnotationTypeDef.py
SmartAnno/utils/ConfigReader.py
SmartAnno/utils/DBInitiater.py
SmartAnno/utils/DBToDataframe.py
SmartAnno/utils/DataSetChooser.py
SmartAnno/utils/DocsToDB.py
SmartAnno/utils/IntroStep.py
SmartAnno/utils/KeywordsEmbeddingExtender.py
SmartAnno/utils/KeywordsEmbeddingExtenderSetup.py
SmartAnno/utils/KeywordsFiltering.py
SmartAnno/utils/KeywordsUMLSExtender.py
SmartAnno/utils/KeywordsUMLSExtenderSetup.py
SmartAnno/utils/LinkedHashSet.py
SmartAnno/utils/NoteBookLogger.py
SmartAnno/utils/ReviewMLInit.py
SmartAnno/utils/ReviewMLLoop.py
SmartAnno-1.0.30.dev0.dist-info/METADATA
SmartAnno-1.0.30.dev0.dist-info/WHEEL
SmartAnno-1.0.30.dev0.dist-info/top_level.txt
SmartAnno-1.0.30.dev0.dist-info/RECORD
